[{"id":"cmmdtua2n003z3wt4g1ypj27w","version":1,"filePath":null,"content":"Subject: How Al Noor Dental Reduced No-Shows by 62% (Case Study)\n\nPreview: From 28% no-shows to 11% in 90 days. Here are the exact steps.\n\nHi [First Name],\n\nAl Noor Dental Clinic in Dubai Healthcare C...","changelog":"Initial generation by CMO AI agent","metadata":"{\"model\":\"content-writer\",\"subject_line\":\"How Al Noor Dental Reduced No-Shows by 62% (Case Study)\",\"preview_text\":\"From 28% no-shows to 11% in 90 days. Here are the exact steps.\",\"audience\":\"Prospects, Warm leads\",\"send_time\":\"Tuesday 9:30 AM GST\",\"email_type\":\"case_study\"}","createdAt":"2026-03-05T18:56:43.391Z"}]