{"id":"cmmdtua2i003p3wt4lz7ev81s","projectId":"cmmda4tdu00007oqcfk611gwg","campaignId":"cmmdb3h080001of8lxe3okk5y","type":"email","subtype":"campaign_email","platform":null,"title":"Q1 Newsletter — AI in Patient Engagement","description":null,"status":"APPROVED","currentVersion":1,"metadata":"{\"model\":\"content-writer\",\"subject_line\":\"How AI Is Reshaping Patient Engagement in 2026\",\"preview_text\":\"Three trends every practice operator should watch this quarter.\",\"audience\":\"All subscribers, Healthcare decision-makers\",\"send_time\":\"Tuesday 9:00 AM GST\",\"email_type\":\"newsletter\"}","tags":null,"createdAt":"2026-03-05T18:56:43.386Z","updatedAt":"2026-03-05T18:56:43.386Z","versions":[{"id":"cmmdtua2i003r3wt4zaa1ij5v","assetId":"cmmdtua2i003p3wt4lz7ev81s","version":1,"filePath":null,"content":"Subject: How AI Is Reshaping Patient Engagement in 2026\n\nPreview: Three trends every practice operator should watch this quarter.\n\nHi [First Name],\n\nThe new year is bringing significant shifts in how healthcare practices connect with patients. Here are three developments worth your attention.\n\n1. WhatsApp Business API Adoption Accelerates\nIn the GCC, 91% of patients now prefer WhatsApp for healthcare communication. Practices that have adopted WhatsApp-first engagement report 2.4x higher appointment confirmation rates compared to SMS-only systems. If your practice has not made this transition yet, Q1 is the time.\n\n2. Predictive No-Show Models Go Mainstream\nThe days of one-size-fits-all reminders are ending. AI models can now predict which specific appointments are at high risk of no-showing, allowing practices to intervene proactively. Early adopters are seeing no-show rates drop below 10%.\n\n3. Patient Experience as a Competitive Advantage\nA recent survey of 1,200 patients in the UAE found that 67% would switch providers for a better scheduling and communication experience, even if clinical quality was equivalent. The operational experience surrounding care is now as important as the care itself.\n\nWhat We Are Working On\nThis quarter, we are rolling out enhanced multilingual support (Arabic, English, Hindi, and Urdu) and deeper integrations with major practice management systems. If you are interested in being among the first to try these features, reply to this email.\n\nResources\n- New blog: \"Why Patient Engagement Platforms Matter in 2026\" [Link]\n- Upcoming webinar: \"Reducing No-Shows with AI\" on January 30 [Register]\n- ROI calculator: Estimate your practice's revenue recovery potential [Try it]\n\nWe are here to help. Reply to this email or book a 15-minute call with our team.\n\nBest,\nThe Zavis Team","metadata":"{\"model\":\"content-writer\",\"subject_line\":\"How AI Is Reshaping Patient Engagement in 2026\",\"preview_text\":\"Three trends every practice operator should watch this quarter.\",\"audience\":\"All subscribers, Healthcare decision-makers\",\"send_time\":\"Tuesday 9:00 AM GST\",\"email_type\":\"newsletter\"}","changelog":"Initial generation by CMO AI agent","createdAt":"2026-03-05T18:56:43.387Z","feedbacks":[]}],"brandChecks":[]}